README.md
src/bacon_five.png
src/decode_five_strips_of_bacon.py
src/encode_five_strips_of_bacon.py
src/main.py
five_strips_of_bacon-1.0.3.dist-info/METADATA
five_strips_of_bacon-1.0.3.dist-info/WHEEL
five_strips_of_bacon-1.0.3.dist-info/entry_points.txt
five_strips_of_bacon-1.0.3.dist-info/RECORD
