Metadata-Version: 2.1
Name: five-strips-of-bacon
Version: 1.0.3
Summary: Encode/Decode messages using five simultaneous bacon ciphers.
Author: Odyhibit
Author-email: josh.2990@gmail.com
Requires-Python: >=3.8,<4.0
Classifier: Programming Language :: Python :: 3
Classifier: Programming Language :: Python :: 3.8
Classifier: Programming Language :: Python :: 3.9
Classifier: Programming Language :: Python :: 3.10
Classifier: Programming Language :: Python :: 3.11
Classifier: Programming Language :: Python :: 3.12
Requires-Dist: customtkinter (>=5.2,<6.0)
Requires-Dist: pillow (>=9,<10)
